kaggle_utils/__init__.py
kaggle_utils/utils.py
kaggle_utils-0.0.9.dist-info/METADATA
kaggle_utils-0.0.9.dist-info/WHEEL
kaggle_utils-0.0.9.dist-info/top_level.txt
kaggle_utils-0.0.9.dist-info/RECORD
