Metadata-Version: 2.1
Name: kaggle_utils
Version: 0.0.9
Summary: Contains useful functions and classes
Author: Vikas Sanwal
Author-email: <vikassnwl@gmail.com>
Keywords: python
Classifier: Development Status :: 1 - Planning
Classifier: Intended Audience :: Developers
Classifier: Programming Language :: Python :: 3
Classifier: Operating System :: Unix
Classifier: Operating System :: MacOS :: MacOS X
Classifier: Operating System :: Microsoft :: Windows
